hospital_sim/__init__.py
hospital_sim/main.py
hospital_sim-0.0.3.dist-info/LICENSE
hospital_sim-0.0.3.dist-info/METADATA
hospital_sim-0.0.3.dist-info/WHEEL
hospital_sim-0.0.3.dist-info/RECORD
