Metadata-Version: 2.3
Name: hospital-sim
Version: 0.0.3
Summary: HospitalSim - Swarms
License: MIT
Keywords: artificial intelligence,deep learning,optimizers,Prompt Engineering
Author: Kye Gomez
Author-email: kye@swarms.world
Requires-Python: >=3.10,<4.0
Classifier: Development Status :: 4 - Beta
Classifier: Intended Audience :: Developers
Classifier: License :: OSI Approved :: MIT License
Classifier: Programming Language :: Python :: 3
Classifier: Programming Language :: Python :: 3.10
Classifier: Programming Language :: Python :: 3.11
Classifier: Programming Language :: Python :: 3.12
Classifier: Programming Language :: Python :: 3.13
Classifier: Programming Language :: Python :: 3.9
Classifier: Topic :: Scientific/Engineering :: Artificial Intelligence
Requires-Dist: chromadb
Requires-Dist: loguru
Requires-Dist: pydantic
Requires-Dist: swarms
Project-URL: Documentation, https://github.com/The-Swarm-Corporation/HospitalSim
Project-URL: Homepage, https://github.com/The-Swarm-Corporation/HospitalSim
Project-URL: Repository, https://github.com/The-Swarm-Corporation/HospitalSim
